setup.cfg
setup.py
reltime/__init__.py
reltime/reltime.py
reltime.egg-info/PKG-INFO
reltime.egg-info/SOURCES.txt
reltime.egg-info/dependency_links.txt
reltime.egg-info/entry_points.txt
reltime.egg-info/requires.txt
reltime.egg-info/top_level.txt
reltime.egg-info/zip-safe
reltime/tests/__init__.py
reltime/tests/test_reltime.py