Metadata-Version: 1.1
Name: reltime
Version: 0.2.0
Summary: find and normalize time information in unstructured text
Home-page: http://live.xyz
Author: Mark Brenckle
Author-email: mark@liveapp.com
License: MIT
Download-URL: https://github.com/calendreco/reltime/archive/v0.2.tar.gz
Keywords: relative,time,normalize,text,date
Platform: UNKNOWN
